ontolearn_light/__init__.py
ontolearn_light/abstracts.py
ontolearn_light/concept_generator.py
ontolearn_light/data_struct.py
ontolearn_light/ea_utils.py
ontolearn_light/fitness_functions.py
ontolearn_light/knowledge_base.py
ontolearn_light/learning_problem.py
ontolearn_light/metrics.py
ontolearn_light/search.py
ontolearn_light/utils/__init__.py
ontolearn_light/utils/log_config.py
ontolearn_light/utils/oplogging.py
ontolearn_light/utils/static_funcs.py
ontosample/__init__.py
ontosample/_base.py
ontosample/classic_samplers.py
ontosample/lpc_samplers.py
ontosample/lpf_samplers.py
ontosample-0.2.6.dist-info/LICENSE
ontosample-0.2.6.dist-info/METADATA
ontosample-0.2.6.dist-info/WHEEL
ontosample-0.2.6.dist-info/top_level.txt
ontosample-0.2.6.dist-info/RECORD
