Metadata-Version: 2.1
Name: ontosample
Version: 0.2.6
Summary: Ontosample is a package that offers different sampling techniques for OWL ontologies.
Home-page: https://github.com/alkidbaci/OntoSample
Author: Alkid Baci
Author-email: alkid1baci@gmail.com
Classifier: Programming Language :: Python :: 3.10
Classifier: License :: OSI Approved :: MIT License
Classifier: Topic :: Scientific/Engineering
Requires-Python: >=3.10.13
License-File: LICENSE
Requires-Dist: matplotlib >=3.3.4
Requires-Dist: owlready2 ==0.40
Requires-Dist: torch >=1.7.1
Requires-Dist: pandas >=1.5.0
Requires-Dist: sortedcontainers >=2.4.0
Requires-Dist: owlapy ==1.3.3
Requires-Dist: requests >=2.31.0
Requires-Dist: deap >=1.3.1
